netbox_sync_status/__init__.py
netbox_sync_status/filtersets.py
netbox_sync_status/forms.py
netbox_sync_status/models.py
netbox_sync_status/navigation.py
netbox_sync_status/tables.py
netbox_sync_status/template_content.py
netbox_sync_status/urls.py
netbox_sync_status/version.py
netbox_sync_status/views.py
netbox_sync_status/api/__init__.py
netbox_sync_status/api/serializers.py
netbox_sync_status/api/urls.py
netbox_sync_status/api/views.py
netbox_sync_status/jobs/__init__.py
netbox_sync_status/jobs/cleanup.py
netbox_sync_status/migrations/0001_netbox_sync_status.py
netbox_sync_status/migrations/0002_netbox_sync_status.py
netbox_sync_status/migrations/0003_netbox_sync_status.py
netbox_sync_status/migrations/__init__.py
netbox_sync_status/templates/__init__.py
netbox_sync_status/templates/netbox_sync_status/sync_status.html
netbox_sync_status/templates/netbox_sync_status/sync_status_buttons.html
netbox_sync_status/templates/netbox_sync_status/syncstatus_list.html
netbox_sync_status/templates/netbox_sync_status/syncsystem.html
netbox_sync_status-2.0.8.dist-info/licenses/LICENSE
netbox_sync_status-2.0.8.dist-info/METADATA
netbox_sync_status-2.0.8.dist-info/WHEEL
netbox_sync_status-2.0.8.dist-info/top_level.txt
netbox_sync_status-2.0.8.dist-info/RECORD
