Metadata-Version: 2.4
Name: netbox-sync-status
Version: 2.0.8
Summary: Sync Status for netbox objects
Home-page: https://github.com/jysk-network/netbox-sync-status
Author: Patrick Falk Nielsen
Author-email: panie@jysk.com
License-File: LICENSE
Dynamic: author
Dynamic: author-email
Dynamic: description
Dynamic: description-content-type
Dynamic: home-page
Dynamic: license-file
Dynamic: summary
